{
 "chapter": "ch3",
 "title": "船艙裡的靜止",
 "startScene": "C0-1",
 "evidenceNames": {
  "S5": "《對話》的船艙頁",
  "G1": "航船桅頂落石",
  "G2": "船艙共同運動",
  "G3": "加速／減速對照",
  "G4": "雙參考物對照",
  "G5": "反對失效，不等於主張得證"
 },
 "evidenceSummary": {
  "S5": "書中用共同運動回應「地球若動，落石就該落後」的反對；它提出待驗預測，不是實驗結果。",
  "G1": "停船基準與三次穩速落石：石頭相對船落在桅腳附近。",
  "G2": "停船與穩速時，封閉船艙中的滴水與拋接近乎相同。",
  "G3": "放手後加速會使落點偏後，減速會使落點偏前；運動改變會留下相對偏移。",
 "G4": "同一事件的岸上與船上紀錄；分開逐拍讀、配對同號鼓點，再扣除桅杆位置後可互相轉換。",
 "G5": "實驗排除『船若前進，落石必落後』的反對，但沒有直接量到地球在動。"
 },
 "publicDemo": {
  "purpose": "船才回港，岸上已有人只傳「第一回落後」，也有人只傳「後來都在桅腳」。艦長因此要求公開重做：每個落點都必須連同船況、鼓點、岸標與釋放方式一起展示。",
  "tokenRule": "木籌不是賭錢，也不是拿來投票決定真相。它只留下每個人實驗前的判斷，不讓人看完結果才改口。",
  "steps": [
   {"id":"baseline","speaker":"艦長","question":"我先替反對者問：沒有停船基準，誰知道船動時的落點算不算改變？","action":"公開停船時的落點基準","reply":"艦長：基準與散布都掛出來。這一項我認。"},
   {"id":"stable-window","speaker":"商人","question":"你們是不是只挑了一段看起來最漂亮的船速？","action":"公開怎麼判定近似穩速","reply":"艾蒂安：鼓點和岸標都留著，任何人都能重新判斷這段船速。"},
   {"id":"no-push","speaker":"船員","question":"放手的人若暗中推一下，也能做出漂亮結果。","action":"交由不押任何落點的馬蒂厄操作門閂","reply":"馬蒂厄：從停船基準到公開重做，門閂都由我抽。學者和船長都沒有碰。"},
   {"id":"seal-prediction","speaker":"商人","question":"結果出來後，誰都能說自己早就猜中。原先的話留在哪裡？","action":"把預測木籌封存在三格記錄板","reply":"伽桑狄：每枚木籌的位置先記下，結果出來後誰都不能移動。它不決定真相，只防止改口。"},
   {"id":"repeat","speaker":"槳手","question":"一次落在桅腳，也可能只是運氣。","action":"照同一做法公開重做三次","reply":"艦長：三次都留下。誰要談落點，就把三次和當時的船況一起談。"}
  ]
 },
 "scenes": [
  {
   "id": "C0-1",
   "title": "馬賽港・頁面翻了三十二年",
   "nodes": [
    {"id":"n1","type":"line","speaker":"stage","text":"1609 年，旅人筆記在伽利略追向天空的那頁停了一瞬。問題沒有跟著他離場。","next":"n1a"},
    {"id":"n1a","type":"line","speaker":"旅人(你)","text":"（指腹按住空白的下一頁）我以為下一頁還會是他的工作室。可伽利略追向天空，沒有回頭。","next":"n1b"},
    {"id":"n1b","type":"line","speaker":"stage","text":"1632 年，他在《對話》裡換了一個問法：船若向前，桅頂的石頭落在哪裡？","next":"n1c"},
    {"id":"n1c","type":"line","speaker":"旅人(你)","text":"三十二年。對我只是幾次翻頁；對他，卻是一生快走到盡頭。我第一次明白：我不會永遠跟著同一位科學家。","next":"n1d"},
    {"id":"n1d","type":"system","speaker":"system","text":"1640 年秋，法國・馬賽。港口沒有熟悉的聲音。","next":"n1e"},
    {"id":"n1e","type":"line","speaker":"旅人(你)","text":"（翻到筆記裡抄下的那一頁）我留下的只有《對話》裡那艘船，和一個還沒真正做過的問題。","next":"n2"},
    {"id":"n2","type":"line","speaker":"stage","text":"海鳥、纜繩與槳帆船。貨箱上坐著一位神父，海風每次掀頁，他都把同一頁壓回去。","next":"n3"},
    {"id":"n3","type":"line","speaker":"伽桑狄","text":"（按住又被海風吹起的書頁，抬眼）早安。你一直盯著這本書——想找哪一頁？","next":"n4"},
    {"id":"n4","type":"line","speaker":"旅人(你)","text":"（這才收回視線，指向他拇指壓住的段落）抱歉，我盯得太久了。談船的那一頁。","next":"n5"},
    {"id":"n5","type":"line","speaker":"伽桑狄","text":"（把書轉向旅人）伽利略，《對話》。第二日。船。","next":"n6"},
    {"id":"n6","type":"line","speaker":"旅人(你)","text":"他把船寫進書裡。","next":"n7"},
    {"id":"n7","type":"line","speaker":"伽桑狄","text":"我想把書帶到海上。（闔上書，抬手指向桅頂）那顆石頭從那裡鬆手，船正在前進時，它會落在哪裡？","next":"n7a"},
    {"id":"n7a","type":"line","speaker":"stage","text":"海風吹過書頁。這次接過問題的人，不是伽利略，而是伽桑狄。","next":"s1"},
    {"id":"s1","type":"system","speaker":"system","text":"取得《對話》的船艙頁。它提出可受審的條件，尚不是實驗證據。","effects":[{"evidence":"S5"}],"next":"g1"},
    {"id":"g1","type":"goto","scene":"C0-2"}
   ]
  },
  {
   "id": "C0-2",
   "title": "先把答案留下",
   "nodes": [
    {"id":"n1","type":"line","speaker":"stage","text":"踏板旁，艦長正低頭核對裝貨單。馬蒂厄守在一旁，每搬上一件貨，就在木牌上劃一道。伽桑狄的手勢越過兩人，指向桅頂。","next":"n1a"},
    {"id":"n1a","type":"line","speaker":"艦長","text":"（頭也沒抬）桅杆上沒有貨。（沒聽見水手回答，這才抬頭）……你們在看桅杆？","next":"n1b"},
    {"id":"n1b","type":"line","speaker":"伽桑狄","text":"（闔起《對話》，走到踏板前）若你肯借船，我想照書裡的說法做一次實驗：船往前時，從桅頂放下石頭，看它落在哪裡。","next":"n1c"},
    {"id":"n1c","type":"line","speaker":"艦長","text":"（把裝貨單捲起，仍擋在踏板前）船可以借。先說好：做出什麼，就寫什麼。別拿我的名字替沒弄清楚的事撐場面。","next":"n2"},
    {"id":"n2","type":"line","speaker":"艦長","text":"船往前，石頭往下。當然落在後面。你從奔馬上跳下來，也不會停在馬鞍正下方。","next":"n2a"},
    {"id":"n2a","type":"line","speaker":"伽桑狄","text":"（把《對話》翻回落石那一段）你不是第一個這樣算。有人把同一句話搬到地面上：地球若在轉，塔也跟著走；塔頂落下的石頭，就該落在塔後。","next":"n2b"},
    {"id":"n2b","type":"line","speaker":"艦長","text":"（視線從桅頂落到書上）可塔頂放下的石頭，一向落在塔腳。","next":"n2c"},
    {"id":"n2c","type":"line","speaker":"伽桑狄","text":"正因為石頭落在塔腳，有人才說：地球不可能在動。","next":"n2d"},
    {"id":"n2d","type":"line","speaker":"艦長","text":"所以你想借我的船，證明地球在動？","next":"n2e"},
    {"id":"n2e","type":"line","speaker":"伽桑狄","text":"不。我只查一件事：船向前時，石頭是不是就一定落後。若這句話不對，就不能再拿它反對地球運動；至於地球究竟動不動，這艘船量不到。","next":"n3"},
    {"id":"n3","type":"line","speaker":"艦長","text":"（拿出三枚木籌，在桌上排開）那就把各自的答案先留下。不賭錢。誰想錯了，誰自己把那枚木籌翻過來。","next":"n3a"},
    {"id":"n3a","type":"line","speaker":"艦長","text":"不是我認定你們會說謊。是結果一出來，人最容易把自己原先說過的話，記成另一個樣子。先寫你的。","next":"n3b"},
    {"id":"n3b","type":"line","speaker":"伽桑狄","text":"（在木籌上寫「桅腳」）石頭鬆手以前，本來就和船一起往前。我預測它不會突然丟掉這份前行。","next":"n3c"},
    {"id":"n3c","type":"line","speaker":"艦長","text":"既然你已有答案，還做什麼實驗？","next":"n3d"},
    {"id":"n3d","type":"line","speaker":"伽桑狄","text":"我有的是推想，不是這艘船的結果。書上說的是走穩的船；你的船會離岸、加槳，也會收槳。我想知道差別出在哪裡。","next":"n3e"},
    {"id":"n3e","type":"line","speaker":"艦長","text":"（把另一枚木籌推給旅人）那你呢？別等石頭落地，才決定自己原本相信什麼。","next":"n3f"},
    {"id":"n3f","type":"line","speaker":"旅人(你)","text":"（寫下「桅腳」）我知道書上怎麼回答。我還沒看過海怎麼回答。","next":"s0"},
    {"id":"s0","type":"system","speaker":"system","text":"旅人的木籌已封存在桅腳格。這不是猜題，而是把已知推論交給實驗受審。","effects":[{"flag":["initialPrediction","foot"]}],"next":"n3g"},
    {"id":"n3g","type":"line","speaker":"stage","text":"艦長把寫著「船尾」的木籌壓進第三格，名字朝外。","next":"n3h"},
    {"id":"n3h","type":"line","speaker":"艦長","text":"（轉向馬蒂厄）從停船那一回開始，門閂由你抽。鼓點、岸標、落點，也由你收。","next":"n3i"},
    {"id":"n3i","type":"line","speaker":"馬蒂厄","text":"照原樣記？","next":"n3j"},
    {"id":"n3j","type":"line","speaker":"艦長","text":"照原樣。包括不合我意的。","next":"n3k"},
    {"id":"n3k","type":"line","speaker":"馬蒂厄","text":"（把空白記錄板夾到臂下）那船長也不能改。","next":"n3l"},
    {"id":"n3l","type":"line","speaker":"艦長","text":"尤其不能替我改。","next":"g1"},
    {"id":"g1","type":"goto","scene":"C0-3"}
   ]
  },
  {
   "id": "C0-3",
   "title": "把句子拆成零件",
   "nodes": [
    {"id":"n1","type":"line","speaker":"艦長","text":"（用裝貨單敲了敲踏板）你要借船，先講清楚要我配合什麼。船往哪開、開多快、什麼時候放手——講不出來就別上船。","next":"n1a"},
    {"id":"n1a","type":"line","speaker":"伽桑狄","text":"（沉默片刻，翻開《對話》，把書裡的說法拆抄在六張紙上）……你問得比書仔細。","next":"q1"},
    {"id":"q1","type":"choice","speaker":"system","text":"艦長要的是能照著做的交代。哪三張真正少不得？","options":[
     {"id":"right","text":"船近似直線前進、速度近似不變、放手時不額外推石頭","next":"n2"},
     {"id":"wind","text":"海面完全無風、船一定向東、石頭來自比薩","next":"r1"},
     {"id":"mix","text":"船近似直線前進、海面完全無風、船一定向東","next":"r2"}
    ]},
    {"id":"r1","type":"line","speaker":"艦長","text":"（把「向東」與「來自比薩」兩張卡彈回桌上）連船往哪裡開、石頭哪裡出生都要指定？這不是定律，是航程表。","next":"q1"},
    {"id":"r2","type":"line","speaker":"艦長","text":"（把「完全無風」與「向東」推回去）風有沒有，我會記；往哪裡開，也可以換一趟。你還沒告訴我，船要不要走穩、放手的人能不能多推。","next":"q1"},
    {"id":"n2","type":"line","speaker":"伽桑狄","text":"（把選中的三張推到艦長面前）直線、走穩、放手時不多推。先在岸邊做一回，再出港；船若改了速度，也另記。","next":"n3"},
    {"id":"n3","type":"line","speaker":"艦長","text":"（用指節依次敲過三張紙）我掌舵，船走得穩不穩由我交代。馬蒂厄碰門閂、收原始記錄。你們可以看，可以問，不能替他補一筆。","next":"n3a"},
    {"id":"n3a","type":"line","speaker":"馬蒂厄","text":"若我做錯？","next":"n3b"},
    {"id":"n3b","type":"line","speaker":"伽桑狄","text":"照樣留下來。錯的操作也是結果的一部分。","next":"n4"},
    {"id":"n4","type":"line","speaker":"stage","text":"艦長把鼓槌交給馬蒂厄，又把一張空白紙交給留在岸上的艾蒂安。","next":"n5"},
    {"id":"n5","type":"line","speaker":"艦長","text":"馬蒂厄照固定節拍敲鼓。艾蒂安，每聽一聲，就在紙上記船到了哪個岸標。","next":"n5a"},
    {"id":"n5a","type":"line","speaker":"馬蒂厄","text":"（在自己的紙上畫下同一串鼓點）我也記放手發生在哪一聲。回來把同號鼓點對上，就不用靠誰說自己記得。","next":"n5b"},
    {"id":"n5b","type":"line","speaker":"艾蒂安","text":"相鄰兩聲之間，船走過的距離若差不多，就是走穩了；一段比一段長，就是還在加速。","next":"n5c"},
    {"id":"n5c","type":"line","speaker":"艦長","text":"正是。往後誰說船走穩了，先把這兩張紙拿出來。","next":"g1"},
    {"id":"g1","type":"goto","scene":"C1-1"}
   ]
  },
  {
   "id":"C1-1","title":"停船基準","nodes":[
    {"id":"n1","type":"line","speaker":"stage","text":"船繫在碼頭。桅腳下鋪細沙；旅人拉好鉛垂線，艾蒂安守著岸標，馬蒂厄站在門閂旁。","next":"n2"},
    {"id":"n2","type":"line","speaker":"stage","text":"馬蒂厄先用手放開石球。石球在沙上歪向一側。","next":"n2a"},
    {"id":"n2a","type":"line","speaker":"馬蒂厄","text":"（看著自己的手）我以為只是鬆開。手指還是推了它一下。","next":"n2b"},
    {"id":"n2b","type":"line","speaker":"伽桑狄","text":"那就換門閂。讓放手只做一件事：不再托住它。","next":"e1"},
    {"id":"e1","type":"embed","system":"ship","phase":"baseline","hint":"校準鉛垂，選擇不額外推石頭的釋放方式，完成三次乾淨的停船基準。","until":{"ship":"baseline"},"next":"n3"},
    {"id":"n3","type":"line","speaker":"艾蒂安","text":"（蹲在沙盤旁，用繩圈住三個落點）三個點都在中央附近。不是同一個洞，但擠在一個手掌裡。","next":"n3a"},
    {"id":"n3a","type":"line","speaker":"馬蒂厄","text":"（把三次落點逐一抄上記錄板）停船、門閂、三次。原樣留下。","next":"n4"},
    {"id":"n4","type":"line","speaker":"伽桑狄","text":"（把「完全同點」劃掉，改寫成「散布範圍」）從現在起，只說它落在這個範圍。","next":"g1"},
    {"id":"g1","type":"goto","scene":"C1-2"}
   ]
  },
  {
   "id":"C1-2","title":"搶跑的船","nodes":[
    {"id":"n1","type":"line","speaker":"stage","text":"船離岸。槳聲由慢轉快。岸上的艾蒂安揮旗，馬蒂厄抽開門閂——石球重重落在桅腳後方。","next":"n2"},
    {"id":"n2","type":"line","speaker":"艦長","text":"（量完落點，把尺橫在沙痕與桅腳之間）船尾。第一回，是我押中了。先別替書找理由；把這一筆照原樣留著。","next":"e1"},
    {"id":"e1","type":"embed","system":"ship","phase":"first-failure","hint":"重現搶跑的一筆，核對鼓點與岸標，找出哪個條件沒有站穩。","until":{"ship":"failure"},"next":"q1"},
    {"id":"q1","type":"choice","speaker":"system","text":"這筆異常最值得先查什麼？","options":[
     {"id":"repeat","text":"不看條件，再做一次","next":"r1"},
     {"id":"weight","text":"換一顆比較輕的石頭","next":"r2"},
     {"id":"speed","text":"核對放手前後，船怎麼走","next":"n3"}
    ]},
    {"id":"r1","type":"line","speaker":"伽桑狄","text":"可以重做。但先找出哪一步出了問題；不然再做一次，還是同樣的亂。","next":"q1"},
    {"id":"r2","type":"line","speaker":"艦長","text":"剛才談的是船追過石頭，怎麼忽然變成石頭的體重？","next":"q1"},
    {"id":"n3","type":"line","speaker":"旅人(你)","text":"放手前後，船的速度一樣嗎？","next":"n3b"},
    {"id":"n3b","type":"line","speaker":"stage","text":"船靠回碼頭。艾蒂安把岸標紙遞上甲板；馬蒂厄將鼓點紙攤在旁邊，兩張紙標著同一串鼓點。","next":"n3c"},
    {"id":"n3c","type":"line","speaker":"馬蒂厄","text":"（點住放手記號）我在第二聲抽門閂。岸上這張，記的是每一聲鼓響時，船走到哪個岸標。","next":"n3a"},
    {"id":"n3a","type":"line","speaker":"艦長","text":"（拿過兩張紙，只看了片刻）……不一樣。（把岸標紙轉向眾人）這一段、這一段、這一段——一段比一段長。船那時還在加速。（停了一下）落後是真的。可我不知道船走穩了會怎樣。","next":"n4"},
    {"id":"n4","type":"line","speaker":"stage","text":"伽桑狄在落點紙上方補寫「加速中」。","next":"n5"},
    {"id":"n5","type":"line","speaker":"艦長","text":"（轉向馬蒂厄）下一回還是你。等鼓點穩了、三段岸標也走得一樣，再抽門閂。（看向伽桑狄）別說我只借給你們一艘搶跑的船。","next":"s1"},
    {"id":"s1","type":"system","speaker":"system","text":"保留失敗紀錄：搶跑的船。它會在之後成為加速度邊界的證據。","effects":[{"flag":["failureDiagnosed","1"]}],"next":"g1"},
    {"id":"g1","type":"goto","scene":"C1-3"}
   ]
  },
  {
   "id":"C1-3","title":"等船安靜下來","nodes":[
    {"id":"n1","type":"line","speaker":"艦長","text":"（在第三段等距岸標下畫線）鼓點穩定還不夠。等連續三段岸標走得差不多，馬蒂厄，再抽門閂。","next":"e1"},
    {"id":"e1","type":"embed","system":"ship","phase":"steady-mast","hint":"選出近似穩速窗口，完成三次航行落石。","until":{"ship":"g1"},"next":"n2"},
    {"id":"n2","type":"line","speaker":"馬蒂厄","text":"（核對落點）桅腳。","next":"n2a"},
    {"id":"n2a","type":"line","speaker":"艦長","text":"再來。","next":"n2b"},
    {"id":"n2b","type":"line","speaker":"stage","text":"同一段穩速窗口又做兩回。馬蒂厄每次都等到鼓點與岸標一致，才抽開門閂。","next":"n2c"},
    {"id":"n2c","type":"line","speaker":"艾蒂安","text":"（從岸上高舉紙帶）三回都一樣！船一直往前，石頭也一直往前。","next":"n3"},
    {"id":"n3","type":"line","speaker":"艦長","text":"（蹲下，把新落點與停船時的沙圈疊著看）三回都在桅杆底下，鼓點和岸標也站得住。","next":"n3a"},
    {"id":"n3a","type":"line","speaker":"馬蒂厄","text":"（看向船尾格）要把你的木籌翻過來嗎？","next":"n3b"},
    {"id":"n3b","type":"line","speaker":"艦長","text":"還不到。甲板上的風還沒有回答。","next":"n4"},
    {"id":"n4","type":"line","speaker":"伽桑狄","text":"（把岸上紙帶與甲板沙圈並排）岸上看見它向前，船上看見它落在桅腳。兩筆都先留下。","next":"g1"},
    {"id":"g1","type":"goto","scene":"C1-4"}
   ]
  },
  {
   "id":"C1-4","title":"風的辯護","nodes":[
    {"id":"n1","type":"line","speaker":"艦長","text":"（抹過甲板上的風向線，沒有碰結果紙）別急著把我的名字寫上去。甲板有風；也許是空氣把石頭帶回桅腳。這一關沒過，這張結果就別拿去碼頭上說服人。","next":"n2"},
    {"id":"n2","type":"line","speaker":"旅人(你)","text":"那就在封閉船艙裡做，先把甲板風排除掉。","next":"n3"},
    {"id":"n3","type":"line","speaker":"伽桑狄","text":"（推開艙門）那就先查風。若船艙裡仍得到同樣的結果，你就不能再把落點算在甲板風頭上。","next":"g1"},
    {"id":"g1","type":"goto","scene":"C2-1"}
   ]
  },
  {
   "id":"C2-1","title":"船艙裡的房間","nodes":[
    {"id":"n1","type":"line","speaker":"stage","text":"低矮船艙裡看不見岸。馬蒂厄守著滴水壺與軟布球；艦長留在舵邊，照岸標把船走穩。","next":"n2"},
    {"id":"n2","type":"line","speaker":"伽桑狄","text":"（把書上飛蟲與魚的兩行劃掉，只留下滴水和拋接）我們不養飛蟲，也不折磨魚。停船與穩速，各做這兩件事就夠了。","next":"e1"},
    {"id":"e1","type":"embed","system":"ship","phase":"cabin","hint":"完成停船／穩速兩種狀態下的滴水與拋接四格比較。","until":{"ship":"g2"},"next":"q1"},
    {"id":"q1","type":"choice","speaker":"system","text":"四格結果最精確的解釋是什麼？","options":[
     {"id":"still","text":"所以船其實沒有動","next":"r1"},
     {"id":"shared","text":"船、器材、空氣與我們原本就一起前進","next":"n3"}
    ]},
    {"id":"r1","type":"line","speaker":"伽桑狄","text":"岸上的旗號正等距掠過——船在前進，而且走得很穩。你不能只看船艙，就忽略甲板上的紀錄。","next":"q1"},
    {"id":"n3","type":"line","speaker":"馬蒂厄","text":"停船，水進碗；穩速，水也進碗。球兩回都落回原位附近。","next":"n3a"},
    {"id":"n3a","type":"line","speaker":"旅人(你)","text":"（接住落回掌心的布球）鬆手只是不再接觸它，不會拿走它原本已有的前行。","next":"n4"},
    {"id":"n4","type":"line","speaker":"艦長","text":"（在艙門口站了一會，指向滴水碗）這裡看不出船在動。（又指向甲板上的第一張落點紙）外面那一回，石頭卻落在桅後。同一艘船，同一天——你們要我認哪一邊？","next":"n5"},
    {"id":"n5","type":"line","speaker":"伽桑狄","text":"哪一邊都別丟。先問：兩回的船，走得一樣嗎？","next":"n5a"},
    {"id":"n5a","type":"line","speaker":"艦長","text":"船速。","next":"n5b"},
    {"id":"n5b","type":"line","speaker":"伽桑狄","text":"下一回只改它。","next":"g1"},
    {"id":"g1","type":"goto","scene":"C2-2"}
   ]
  },
  {
   "id":"C2-2","title":"船一改變主意","nodes":[
    {"id":"n1","type":"line","speaker":"stage","text":"回到甲板。馬蒂厄守門閂，艦長站在舵邊。裝置維持不變，這次只改放手之後的船速：加槳，或收槳。","next":"e1"},
    {"id":"e1","type":"embed","system":"ship","phase":"speed-change","hint":"先封存加速與減速的落點預測，至少各做一次；之後仍可自由重做比較。","until":{"ship":"g3"},"next":"n2"},
    {"id":"n2","type":"line","speaker":"馬蒂厄","text":"（把兩張落點紙攤在第一回左右）加速在後，減速在前。第一回跟加速這張同方向。","next":"n3"},
    {"id":"n3","type":"line","speaker":"艦長","text":"（把第一回的落點紙重新攤開）所以第一回看見的落後，不是假的。","next":"n3a"},
    {"id":"n3a","type":"line","speaker":"艦長","text":"我一開始拿奔馬說你們錯。可奔馬會忽快忽慢。","next":"n4"},
    {"id":"n4","type":"line","speaker":"艦長","text":"我看見落後，沒有看錯。我錯在把加速那一回，說成所有向前走的船都會如此。","next":"n4a"},
    {"id":"n4a","type":"line","speaker":"stage","text":"艦長把自己的木籌翻過來，卻沒有收走；名字朝外，仍留在船尾格。伽桑狄把三張落點紙並排釘上，沒有再解釋。","next":"g1"},
    {"id":"g1","type":"goto","scene":"C2-2B"}
   ]
  },
  {
   "id":"C2-2B","title":"船還沒繫牢","nodes":[
    {"id":"n1","type":"line","speaker":"stage","text":"船才靠回石碼頭，纜繩還在水手手裡。踏板外已有人喊：「第一回明明落在後面！」另一頭立刻有人回：「後來三回都在桅腳！」同一天的結果，傳到岸上只剩兩句互相打架的話。","next":"n2"},
    {"id":"n2","type":"line","speaker":"艦長","text":"（聽了一會）我的船才出去一趟，回來已經被你們傳成兩艘了。沒人問它那時走得穩不穩，只挑自己想聽的那一回。","next":"n3"},
    {"id":"n3","type":"line","speaker":"艦長","text":"明天同一時間，當眾再做。鼓點、岸標、門閂，全掛出來。誰要說石頭落後或沒有落後，就連船當時怎麼走一起說。","next":"n4"},
    {"id":"n4","type":"line","speaker":"艦長","text":"（對馬蒂厄）門閂明天還是你抽。別讓押中的人忽然變成自己的證人。","next":"n5"},
    {"id":"n5","type":"line","speaker":"馬蒂厄","text":"包括你？","next":"n6"},
    {"id":"n6","type":"line","speaker":"艦長","text":"尤其包括我。","next":"g1"},
    {"id":"g1","type":"goto","scene":"C2-3"}
   ]
  },
  {
   "id":"C2-3","title":"岸上的紙，船上的紙","nodes":[
    {"id":"n1","type":"line","speaker":"stage","text":"艾蒂安帶回岸上紙帶，馬蒂厄攤開船上紙帶。兩張分開顯示，都標著同一串鼓點。","next":"n2"},
    {"id":"n2","type":"line","speaker":"艾蒂安","text":"（按住岸上紙，沿著鼓點逐一指過）我的石頭往前走。","next":"n3"},
    {"id":"n3","type":"line","speaker":"馬蒂厄","text":"（沿船上紙往下比）我記的是它離桅杆多遠。它幾乎直直落。","next":"n4"},
    {"id":"n4","type":"line","speaker":"伽桑狄","text":"（把燭火挪到兩張紙中間）很好。現在誰要把誰的紙燒掉？","next":"e1"},
    {"id":"e1","type":"embed","system":"ship","phase":"overlay","hint":"先逐拍讀懂兩張紙各自量什麼，再配對同號鼓點，最後扣除同一時刻的桅杆位置。","until":{"ship":"g4"},"next":"n5"},
    {"id":"n5","type":"line","speaker":"旅人(你)","text":"（把同號鼓點一一連直）兩張圖沒有互相推翻。它們只是各自把不同的東西當作不動。","next":"n6"},
    {"id":"n6","type":"line","speaker":"伽桑狄","text":"（用鉛筆敲過兩張紙上的同號鼓點）一句話如果沒先回答『相對誰』，通常只說了一半。","next":"n7"},
    {"id":"n7","type":"line","speaker":"艦長","text":"（站在兩人後方，雙手都沒有碰紙）明天艾蒂安守岸上，馬蒂厄守船上。我只查船況和木籌。","next":"s1"},
    {"id":"s1","type":"system","speaker":"system","text":"取得證據：雙參考物對照。解鎖操作詞：切換參考物。現代整理詞「參考系」留到史實頁。","effects":[{"flag":["referenceNamed","1"]}],"next":"g1"},
    {"id":"g1","type":"goto","scene":"C2-4"}
   ]
  },
  {
   "id":"C2-4","title":"不推之後，留下什麼","nodes":[
    {"id":"n1","type":"line","speaker":"伽桑狄","text":"（把四張紀錄排在《對話》旁，只留一格給結論）現在把話說準。哪一句只說到證據真正支持的範圍？","next":"q1"},
    {"id":"q1","type":"choice","speaker":"system","text":"選出不誇大、也不偷偷造出一股新力的主張。","options":[
     {"id":"forever","text":"物體一旦運動，就會永遠保持任何運動","next":"r1"},
     {"id":"force","text":"石頭裡藏著一股向前的力，持續推它","next":"r2"},
     {"id":"bounded","text":"近似直線穩速、無額外水平推拉時，鬆手不會清除石頭與船共有的前行","next":"n2"}
    ]},
    {"id":"r1","type":"line","speaker":"伽桑狄","text":"（用筆尖點了點一路向下加快的刻度）它明明越落越快。你不能一邊看著向下的運動改變，一邊說任何運動都不變。","next":"q1"},
    {"id":"r2","type":"line","speaker":"伽桑狄","text":"別換個名字，又把那股看不見的推力塞回來。","next":"q1"},
    {"id":"n2","type":"line","speaker":"旅人(你)","text":"不再接觸，不等於把已有的前行歸零。","next":"n2a"},
    {"id":"n2a","type":"line","speaker":"stage","text":"港口官員拿著明日告示的草稿走來，等著送印的工人就站在踏板旁。","next":"n2b"},
    {"id":"n2b","type":"line","speaker":"官員","text":"（把草稿攤開）告示總得讓人一眼看懂，馬賽明天要做成什麼。（照著念）馬賽港，落石實驗，證明地球運動。（抬頭）這樣夠清楚了吧？","next":"n2c"},
    {"id":"n2c","type":"line","speaker":"伽桑狄","text":"（按住告示一角）「證明地球運動」這幾個字，哪一筆已經做完的紀錄給你的？","next":"n2d"},
    {"id":"n2d","type":"line","speaker":"艦長","text":"（看了一眼「證明地球運動」）昨天的我會喜歡這句。一眼就知道誰贏。可今天我知道，一眼看懂，常常只是少看了幾張紙。","next":"n3"},
    {"id":"n3","type":"line","speaker":"伽桑狄","text":"也讓他們看清楚，每一步是怎麼做的。","next":"g1"},
    {"id":"g1","type":"goto","scene":"C3-1"}
   ]
  },
  {
   "id":"C3-1","title":"馬賽港公開驗證","nodes":[
    {"id":"n1","type":"line","speaker":"stage","text":"船員、學生、商人與官員站滿碼頭。每個人先把預測木籌放進船頭、桅腳或船尾的記錄格。艦長那枚翻過面的木籌仍留在船尾，名字朝外。","next":"n1b"},
    {"id":"n1b","type":"line","speaker":"伽桑狄","text":"（把自己的木籌也先放進一格）木籌不是賭錢，也不是拿來投票決定真相。它只留下每個人實驗前的判斷，不讓人看完結果才改口。","next":"n2"},
    {"id":"n2","type":"line","speaker":"艦長","text":"（站到記錄板旁）馬蒂厄抽門閂，艾蒂安記岸標；我只查船況。誰中途換條件，我就叫停。每一步若照約定走完，石頭無論落在哪裡，我都認。","next":"e1"},
    {"id":"e1","type":"embed","system":"ship","phase":"public-demo","hint":"依序公開停船基準、穩速窗口、無額外推石頭、封存預測與三次重複。","until":{"ship":"public"},"next":"n3"},
    {"id":"n3","type":"line","speaker":"stage","text":"馬蒂厄當眾操作門閂。三次落點都聚在桅腳的基準散布附近；艾蒂安公開岸標，馬蒂厄公開鼓點。預測與結果一起留在木板上。","next":"n3a"},
    {"id":"n3a","type":"line","speaker":"馬蒂厄","text":"原紙都在。哪一拍開始走穩，你們自己查。","next":"n4"},
    {"id":"n4","type":"line","speaker":"艦長","text":"門閂從第一回起就由馬蒂厄抽。伽桑狄不碰，我也不碰。條件照約定走完，現在誰若不喜歡結果，不能回頭改做法。","next":"g1"},
    {"id":"g1","type":"goto","scene":"C3-2"}
   ]
  },
  {
   "id":"C3-2","title":"三道公開質詢","nodes":[
    {"id":"n1","type":"line","speaker":"艦長","text":"（站在自己翻過面的木籌旁）風、加速，還有岸上與船上的兩張紀錄，都是我昨天問過的。今天輪到碼頭上的人問；你們自己拿紀錄回答。","next":"n1a"},
    {"id":"n1a","type":"line","speaker":"馬蒂厄","text":"門閂、鼓點與落點原紙都在這裡。問哪一步，就查哪一張。","next":"e1"},
    {"id":"e1","type":"embed","system":"ship","phase":"audit","hint":"為三道質詢各選一張真正能回答它的證據。","until":{"ship":"audit"},"next":"n2"},
    {"id":"n2","type":"line","speaker":"伽桑狄","text":"三個問題都回答了。最後還有一個更難的問題：我們到底證明到哪裡？","next":"g1"},
    {"id":"g1","type":"goto","scene":"C3-3"}
   ]
  },
  {
   "id":"C3-3","title":"最後的誘惑","nodes":[
    {"id":"n1","type":"line","speaker":"官員","text":"（把昨夜的告示重新攤開）結果有了。最後一句，照昨晚那樣印？","next":"n2"},
    {"id":"n2","type":"line","speaker":"stage","text":"排字工人等在一旁。官員把筆尖停在最後一行的空白處。","next":"e1"},
    {"id":"e1","type":"embed","system":"ship","phase":"boundary","hint":"指出這場公開驗證究竟排除了什麼，又沒有直接證明什麼。","until":{"ship":"g5"},"next":"n3"},
    {"id":"n3","type":"line","speaker":"旅人(你)","text":"今天沒有直接量到地球怎麼動。我們只證明了：『船動，石頭就一定落後』這個反對站不住。","next":"n4"},
    {"id":"n4","type":"line","speaker":"艦長","text":"（接過紙，逐字讀完，才落筆）我的船只替今天量到的事作證。這句，我簽。","next":"n5"},
    {"id":"n5","type":"line","speaker":"伽桑狄","text":"（接過簽好的紙，壓在木板中央）這就夠重了。","next":"g1"},
    {"id":"g1","type":"goto","scene":"C3-4"}
   ]
  },
  {
   "id":"C3-4","title":"題名","nodes":[
    {"id":"n1","type":"line","speaker":"stage","text":"人群散去。加速、穩速與減速的三張紀錄仍並排掛在木板上；艦長沒有取下任何一張。","next":"n2"},
    {"id":"n2","type":"line","speaker":"馬蒂厄","text":"不帶走？","next":"n3"},
    {"id":"n3","type":"line","speaker":"艦長","text":"留著。新上船的人若只說「船在動」，先讓他看看這裡其實有三種船況。","next":"n3a"},
    {"id":"n3a","type":"line","speaker":"馬蒂厄","text":"所以往後每一拍還要記？","next":"n3b"},
    {"id":"n3b","type":"line","speaker":"艦長","text":"一開始我讓你記，是因為我以為自己會贏。往後繼續記，是因為我也會錯。","next":"n4"},
    {"id":"n4","type":"line","speaker":"旅人(你)","text":"鬆手之後，沒有誰繼續推它。","next":"n5"},
    {"id":"n5","type":"line","speaker":"伽桑狄","text":"（在手稿首頁落下最後一筆）可它離手的時候，已經在往前走了。","next":"s1"},
    {"id":"s1","type":"system","speaker":"system","text":"第三章《船艙裡的靜止》","next":"g1"},
    {"id":"g1","type":"goto","scene":"CE-1"}
   ]
  },
  {
   "id":"CE-1","title":"兩本書・1642","nodes":[
    {"id":"n1","type":"line","speaker":"stage","text":"紙張、鉛字與油墨。伽桑狄把伽利略的《對話》放在左邊，自己的手稿放在右邊。","next":"n2"},
    {"id":"n2","type":"line","speaker":"伽桑狄","text":"（指腹停在《對話》的船艙頁）他把船寫進書裡。","next":"n3"},
    {"id":"n3","type":"line","speaker":"stage","text":"馬賽的落點紙、船速紀錄與雙紙帶攤在兩本書之間。","next":"n4"},
    {"id":"n4","type":"line","speaker":"伽桑狄","text":"（把三份紀錄依次夾進自己的手稿）我們把書帶到海上。現在，把海帶回書裡。","next":"n5"},
    {"id":"n5","type":"line","speaker":"stage","text":"桌角有一封新到的信：伽利略已於阿爾切特里去世。伽桑狄沒有朗讀，只把《對話》的封面拂平。","next":"g1"},
    {"id":"g1","type":"goto","scene":"CE-2"}
   ]
  },
  {
   "id":"CE-2","title":"旅人筆記・末頁","nodes":[
    {"id":"n1","type":"line","speaker":"stage","text":"筆記畫出兩條路：以船為基準近乎直落；以岸為基準向前彎下。兩條線共用同一串鼓點。","next":"r1"},
    {"id":"r1","type":"review","prompts":["船上與岸上看見的路徑不同，為什麼不代表有人看錯？","這場實驗推翻了哪一個反對？又沒有證明什麼？"],"next":"n2"},
    {"id":"n2","type":"line","speaker":"stage","text":"頁面下方浮出一道未完成的弧。若物體能保留已有的前行，月亮為什麼沒有沿直線離開？","next":"h1"},
    {"id":"h1","type":"histfacts","next":"s1"},
    {"id":"s1","type":"system","speaker":"system","text":"第三章已封存。旅人筆記新增未解問題:「月亮為什麼沒有沿直線離開?」","next":"end"},
    {"id":"end","type":"end"}
   ]
  }
 ]
}
